<!-- ######################################################################################## IO Vision Mode meter -->
<_PNXVMEnabled> 0 </_PNXVMEnabled>
<_PNXVMCharge> 1 </_PNXVMCharge>
<_PNXVMCells> 666 </_PNXVMCells>
<_PNXVMMode> 1 </_PNXVMMode>

<!-- ######################################################################################## IO Grain -->
<_PNXGrainAmount> 0 </_PNXGrainAmount>
<_PNXGrainPhase> 0 </_PNXGrainPhase>
<_PNXGrainColorRed> 1.0 </_PNXGrainColorRed>
<_PNXGrainColorGreen> 1.0 </_PNXGrainColorGreen>
<_PNXGrainColorBlue> 1.0 </_PNXGrainColorBlue>

<!-- ######################################################################################## IO Radar -->
<_PNXShowRadar> 0 </_PNXShowRadar>
<_PNXRadarScale> 0.5 </_PNXRadarScale>

<_PNXRadarXAlign> 1 </_PNXRadarXAlign> <!-- 0: left 0.5: center 1: right -->
<_PNXRadarYAlign> 0 </_PNXRadarYAlign> <!-- 0: top 0.5: center 1: bottom -->

<_PNXRadarXOffset> -160 </_PNXRadarXOffset>
<_PNXRadarYOffset> 10 </_PNXRadarYOffset>

<_PNXRadarMarker1Mode> 0 </_PNXRadarMarker1Mode>
<_PNXRadarMarker1X> 0 </_PNXRadarMarker1X>
<_PNXRadarMarker1Y> 0 </_PNXRadarMarker1Y>

<_PNXRadarMarker2Mode> 0 </_PNXRadarMarker2Mode>
<_PNXRadarMarker2X> 0 </_PNXRadarMarker2X>
<_PNXRadarMarker2Y> 0 </_PNXRadarMarker2Y>

<_PNXRadarMarker3Mode> 0 </_PNXRadarMarker3Mode>
<_PNXRadarMarker3X> 0 </_PNXRadarMarker3X>
<_PNXRadarMarker3Y> 0 </_PNXRadarMarker3Y>

<_PNXRadarMarker4Mode> 0 </_PNXRadarMarker4Mode>
<_PNXRadarMarker4X> 0 </_PNXRadarMarker4X>
<_PNXRadarMarker4Y> 0 </_PNXRadarMarker4Y>

<_PNXRadarMarker5Mode> 0 </_PNXRadarMarker5Mode>
<_PNXRadarMarker5X> 0 </_PNXRadarMarker5X>
<_PNXRadarMarker5Y> 0 </_PNXRadarMarker5Y>

<_PNXRadarMarker6Mode> 0 </_PNXRadarMarker6Mode>
<_PNXRadarMarker6X> 0 </_PNXRadarMarker6X>
<_PNXRadarMarker6Y> 0 </_PNXRadarMarker6Y>

<_PNXRadarMarker7Mode> 0 </_PNXRadarMarker7Mode>
<_PNXRadarMarker7X> 0 </_PNXRadarMarker7X>
<_PNXRadarMarker7Y> 0 </_PNXRadarMarker7Y>

<_PNXRadarMarker8Mode> 0 </_PNXRadarMarker8Mode>
<_PNXRadarMarker8X> 0 </_PNXRadarMarker8X>
<_PNXRadarMarker8Y> 0 </_PNXRadarMarker8Y>

<_PNXRadarMarker9Mode> 0 </_PNXRadarMarker9Mode>
<_PNXRadarMarker9X> 0 </_PNXRadarMarker9X>
<_PNXRadarMarker9Y> 0 </_PNXRadarMarker9Y>

<!-- ######################################################################################## IO Stealth Field meter-->

<_PNXSFShowStealthMeter> 0 </_PNXSFShowStealthMeter>
<_PNXSFMeterStyle> 0 </_PNXSFMeterStyle>
<_PNXSFStability> 1 </_PNXSFStability>
<_PNXSFCharges> 0 </_PNXSFCharges>
<_PNXSFHealth> 1 </_PNXSFHealth>

<!-- ######################################################################################## IO Crosshair-->

<_PNXCrosshairEnabled> 1 </_PNXCrosshairEnabled>
<_PNXCrosshairLength> 16 </_PNXCrosshairLength>
<_PNXCrosshairWidth> 6 </_PNXCrosshairWidth>
<_PNXCrosshairSpread> 0.5 </_PNXCrosshairSpread> <!-- 0.0 to 1.0 -->
<_PNXCrosshairMinOffset> 3 </_PNXCrosshairMinOffset>
<_PNXCrosshairMaxOffset> 128 </_PNXCrosshairMaxOffset>

<!-- ######################################################################################## IO Bullet Time Meter-->

<_PNxBTMeterEnabled> 0 </_PNxBTMeterEnabled>
<_PNxBTMeterAmount> 0 </_PNxBTMeterAmount>
<_PNxBTMeterWarn> 0 </_PNxBTMeterWarn>
<_PNxBTMeterIcon> 0 </_PNxBTMeterIcon>
<_PNxBTMeterIconAnim> 0 </_PNxBTMeterIconAnim> <!-- 0.0 to 1.0 -->

<!-- ######################################################################################## IO Calibrator-->

<_PNXCalibratorEnabled> 0 </_PNXCalibratorEnabled>
<_PNXCalibratorSize> 200 </_PNXCalibratorSize>

<!-- ######################################################################################## Zoom Bar -->

<_PNxZoomBarEnabled> 0 </_PNxZoomBarEnabled>
<_PNxZoomBarFill> 0 </_PNxZoomBarFill>

<!-- ######################################################################################## Scanner -->

<_PNxScannerEnabled> 0 </_PNxScannerEnabled>
<_PNxScannerCursorLine> 0 </_PNxScannerCursorLine>
<_PNxScannerCursorPos> 0 </_PNxScannerCursorPos>
<_PNxScannerCursorIndent> 0 </_PNxScannerCursorIndent>
<_PNxScannerCursorBlink> 0 </_PNxScannerCursorBlink>

<_PNxScannerText1Index> 0 </_PNxScannerText1Index>
<_PNxScannerText2Index> 0 </_PNxScannerText2Index>
<_PNxScannerText3Index> 0 </_PNxScannerText3Index>
<_PNxScannerText4Index> 0 </_PNxScannerText4Index>
<_PNxScannerText5Index> 0 </_PNxScannerText5Index>
<_PNxScannerText6Index> 0 </_PNxScannerText6Index>
<_PNxScannerText7Index> 0 </_PNxScannerText7Index>
<_PNxScannerText8Index> 0 </_PNxScannerText8Index>
<_PNxScannerText9Index> 0 </_PNxScannerText9Index>
<_PNxScannerText10Index> 0 </_PNxScannerText10Index>



<_configActive> 0 </_configActive>



	<image name="PNxBTMeterStatusWarning">
		<systemcolor> &nosystemcolor; </systemcolor>
	
		<visible> <copy src="io()" trait="_configActive" /> </visible>
	
		<zoom> &scale; </zoom>
		<depth> 10 </depth>
		
		<x>0</x>
		<y>0</y>
		<width> <copy src="screen()" trait="width" /> </width>
		<height> <copy src="screen()" trait="height" /> </height>

		<filename> pnx\customPause.dds </filename>
	</image>







<!-- ######################################################################################## Vision Mode meter -->
<rect name="PNXVMMeter">
	<locus> &true; </locus>
	<x>
		<copy> 0 </copy>
		<sub>
			<copy> 131 </copy>
			<mul src="globals()" trait="_duiscale_65" />
		</sub>
		<add src="globals()" trait="_HUDHPInfo_X" />
	</x>
	<y>
		<copy src="HitPoints" trait="y" />
		<sub>
			<copy> 52 </copy>
			<mul src="globals()" trait="_duiscale_65" />
		</sub>
	</y>
	<visible>
		<copy src="io()" trait="_PNXVMEnabled" />
		<eq> 1 </eq>
		<and src="io()" trait="_HUDMode" />
	</visible>
	<image name="PNXVMMeterMeter">
		<depth> -1 </depth>
		<alpha> <copy src="io()" trait="_MeterAlpha" /> </alpha>
		<width>
			<copy> 152 </copy>
			<mul src="globals()" trait="_duiscale_65" />
			<mul src="me()" trait="_Value" />
		</width>
		<height>
			<copy> 20 </copy>
			<mul src="globals()" trait="_duiscale_65" />
		</height>
		<cropx>
			<copy src="parent()" trait="width"/>
			<mul src="me()" trait="_Value"/>
			
		</cropx>
		
		<filename>
			<copy src="globals()" trait="_HUDSolidMeters" />
			<copy src="me()" trait="_filename_" />
		</filename>
		<_filename_0> Interface\HUD\hud_tick_mark.dds </_filename_0>
		<_filename_1> Interface\Shared\solid.dds </_filename_1>
		<zoom>
			<copy src="globals()" trait="_duiscale_65" />
			<mul> 100 </mul>
		</zoom>
		<tile> <not src="globals()" trait="_HUDSolidMeters" /> </tile>
		<x>
			<copy> 151 </copy>
			<mul src="globals()" trait="_duiscale_65" />
		</x>
		<y>
			<copy> 61 </copy>
			<mul src="globals()" trait="_duiscale_65" />
			<sub src="me()" trait="height"/>
		</y>
		<_Value> <copy src="io()" trait="_PNXVMCharge"/> </_Value>
		<systemcolor> <copy src="globals()" trait="_duiHUDMtrSysColor" /> </systemcolor> <!-- DarN CHECK -->
		<brightness> <copy src="globals()" trait="_duiHUDMtrBrightness" /> </brightness>
		<red> <copy src="globals()" trait="_HUDRed" /> </red>
		<green> <copy src="globals()" trait="_HUDGreen" /> </green>
		<blue> <copy src="globals()" trait="_HUDBlue" /> </blue>
	</image>
	<image name="PNXVMMeterMeterBG">
		<visible> <copy src="globals()" trait="_HUDSolidMeters" /> </visible>
		<depth> -2 </depth>
		<filename> solid.dds </filename>
		<texatlas> Interface\InterfaceShared.tai </texatlas>
		<height> <copy src="sibling(VMMeterMeter)" trait="height" /> </height>
		<width>
			<copy> 152 </copy>
			<mul src="globals()" trait="_duiscale_65" />
		</width>
		<x>
			<copy src="sibling(VMMeterMeter)" trait="x" />
			<add src="sibling(VMMeterMeter)" trait="width" />
			<sub src="me()" trait="width" />
		</x>
		<y> <copy src="sibling(VMMeterMeter)" trait="y" /> </y>
		<alpha>
			<copy src="sibling(VMMeterMeter)" trait="alpha" />
			<div> 2 </div>
		</alpha>
		<brightness> <copy src="sibling(VMMeterMeter)" trait="brightness" /> </brightness>
		<systemcolor> <copy src="sibling(VMMeterMeter)" trait="systemcolor" /> </systemcolor> <!-- DarN CHECK -->
		<red> <copy src="globals()" trait="_HUDRed" /> </red>
		<green> <copy src="globals()" trait="_HUDGreen" /> </green>
		<blue> <copy src="globals()" trait="_HUDBlue" /> </blue>
	</image>
	<image name="PNXVMBracket">
		<height>
			<copy> 152 </copy>
			<mul src="globals()" trait="_duiscale_65" />
		</height>
		<width>
			<copy> 512 </copy>
			<mul src="globals()" trait="_duiscale_65" />
		</width>
		<filename> Interface\HUD\glow_hud_left_nv_seperator.dds </filename>
		<zoom> &scale; </zoom>
		<brightness> <copy src="globals()" trait="_duiHUDBrightness" /> </brightness>
		<red> <copy src="globals()" trait="_HUDRed" /> </red>
		<green> <copy src="globals()" trait="_HUDGreen" /> </green>
		<blue> <copy src="globals()" trait="_HUDBlue" /> </blue>
	</image>
	<text name="PNXVMLabel">
		<font> <copy src="globals()" trait="_HUDMeterFont" /> </font>
		<justify> &left; </justify>
		<x>
			<copy> 161 </copy>
			<mul src="globals()" trait="_duiscale_65" />
		</x>
		<y>
			<copy> 7 </copy>
			<mul src="globals()" trait="_duiscale_65" />
		</y>
	
		<_nam_1> NV </_nam_1>
		<_nam_2> HV </_nam_2>
		<_nam_3> EV </_nam_3>
		
		<_name>
			<copy src="io()" trait="_PNXVMMode" />
			<copy src="me()" trait="_nam_" />
		</_name>
		
		<string>
			<copy src="me()" trait="_name" />
		</string>
		
		<brightness> <copy src="globals()" trait="_duiHUDBrightness" /> </brightness>
		<red> <copy src="globals()" trait="_HUDTxtRed" /> </red>
		<green> <copy src="globals()" trait="_HUDTxtGreen" /> </green>
		<blue> <copy src="globals()" trait="_HUDTxtBlue" /> </blue>
	</text>
	<text name="PNXVMCellsText">
		<font> <copy src="globals()" trait="_HUDMeterFont" /> </font>
		<justify> &left; </justify>
		<x>
			<copy> 161 </copy>
			<mul src="globals()" trait="_duiscale_65" />
		</x>
		<y>
			<copy> 79 </copy>
			<mul src="globals()" trait="_duiscale_65" />
		</y>
		<string> <copy src="io()" trait="_PNXVMCells"/> </string>
		<brightness> <copy src="globals()" trait="_duiHUDBrightness" /> </brightness>
		<red> <copy src="globals()" trait="_HUDTxtRed" /> </red>
		<green> <copy src="globals()" trait="_HUDTxtGreen" /> </green>
		<blue> <copy src="globals()" trait="_HUDTxtBlue" /> </blue>
	</text>

</rect>

<!-- ######################################################################################## Grain -->
<rect name="PNXGrainLayer">
	<x>0</x>
	<y>0</y>
	<width>
		<copy src="screen()" trait="width" />
	</width>
	<height><copy src="screen()" trait="height" /></height>
	
	<alpha>
		<copy src="io()" trait="_PNXGrainAmount" />
		<mul>255</mul>
	</alpha>
	<red>
		<copy src="io()" trait="_PNXGrainColorRed" />
		<mul>255</mul>
	</red>
	<green>
		<copy src="io()" trait="_PNXGrainColorGreen" />
		<mul>255</mul>
	</green>
	<blue>
		<copy src="io()" trait="_PNXGrainColorBlue" />
		<mul>255</mul>
	</blue>

	<!-- Explicit copy for each phase for much smoother performance -->
	<image name="Phase1">
		<zoom> &scale; </zoom>
		<depth> -11 </depth>
		<systemcolor> &nosystemcolor; </systemcolor>
		
		<red><copy src="parent()" trait="red" /></red>
		<green><copy src="parent()" trait="green" /></green>
		<blue><copy src="parent()" trait="blue" /></blue>
		<alpha><copy src="parent()" trait="alpha" /></alpha>
		
		<width><copy src="parent()" trait="width" /></width>
		<height><copy src="parent()" trait="height" /></height>
		
		<visible>
			<copy src="io()" trait="_PNXGrainPhase" />
			<eq> 1 </eq>
		</visible>
		
		<filename> pnx\grain1.dds </filename>
	</image>
	
	<image name="Phase2">
		<zoom> &scale; </zoom>
		<depth> -11 </depth>
		<systemcolor> &nosystemcolor; </systemcolor>
		
		<red><copy src="parent()" trait="red" /></red>
		<green><copy src="parent()" trait="green" /></green>
		<blue><copy src="parent()" trait="blue" /></blue>
		<alpha><copy src="parent()" trait="alpha" /></alpha>
		
		<width><copy src="parent()" trait="width" /></width>
		<height><copy src="parent()" trait="height" /></height>
		
		<visible>
			<copy src="io()" trait="_PNXGrainPhase" />
			<eq> 2 </eq>
		</visible>
		
		<filename> pnx\grain2.dds </filename>
		
	</image>
	
	<image name="Phase3">
		<zoom> &scale; </zoom>
		<depth> -11 </depth>
		<systemcolor> &nosystemcolor; </systemcolor>
		
		<red><copy src="parent()" trait="red" /></red>
		<green><copy src="parent()" trait="green" /></green>
		<blue><copy src="parent()" trait="blue" /></blue>
		<alpha><copy src="parent()" trait="alpha" /></alpha>
		
		<width><copy src="parent()" trait="width" /></width>
		<height><copy src="parent()" trait="height" /></height>
		
		<visible>
			<copy src="io()" trait="_PNXGrainPhase" />
			<eq> 3 </eq>
		</visible>
		
		<filename> pnx\grain3.dds </filename>
		
	</image>
	
	<image name="Phase4">
		<zoom> &scale; </zoom>
		<depth> -11 </depth>
		<systemcolor> &nosystemcolor; </systemcolor>
		
		<red><copy src="parent()" trait="red" /></red>
		<green><copy src="parent()" trait="green" /></green>
		<blue><copy src="parent()" trait="blue" /></blue>
		<alpha><copy src="parent()" trait="alpha" /></alpha>
		
		<width><copy src="parent()" trait="width" /></width>
		<height><copy src="parent()" trait="height" /></height>
		
		<visible>
			<copy src="io()" trait="_PNXGrainPhase" />
			<eq> 4 </eq>
		</visible>
		
		<filename> pnx\grain4.dds </filename>
		
	</image>

</rect>


<!-- ######################################################################################## Radar -->
<rect name="PNXRadar">

	<visible>
		<copy src="io()" trait="_PNXShowRadar" />
		<eq> 1 </eq>
		<and>
			<copy src="ActionPoints" trait="visible" />
			<or src="io()" trait="_PNXSelectMode" />
		</and>
	</visible>

	<width>
		<copy>400</copy>
		<mul src="io()" trait="_PNXRadarScale" />
	</width>
	
	<height>
		<copy>400</copy>
		<mul src="io()" trait="_PNXRadarScale" />
	</height>
	
	<x>
		<copy src="screen()" trait="width" />
		<mul src="io()" trait="_PNXRadarXAlign" />
		<sub>
			<copy src="me()" trait="width" />
			<mul src="io()" trait="_PNXRadarXAlign" />
		</sub>
		<add src="io()" trait="_PNXRadarXOffset" />
	</x>
	
	<y>
		<copy src="screen()" trait="height" />
		<mul src="io()" trait="_PNXRadarYAlign" />
		<sub>
			<copy src="me()" trait="height" />
			<mul src="io()" trait="_PNXRadarYAlign" />
		</sub>
		<add src="io()" trait="_PNXRadarYOffset" />
	</y>

	<image name="Background">
		<zoom> &scale; </zoom>
		<depth> 0 </depth>
		
		<x><copy src="parent()" trait="x" /></x>
		<y><copy src="parent()" trait="y" /></y>
		
		<width><copy src="parent()" trait="width" /></width>
		<height><copy src="parent()" trait="height" /></height>
		
		<filename> pnx\radar.dds </filename>
	</image>
	
	<image name="Marker1">
		<include src="pnx\radar_marker.xml" />
		<_Mode><copy src="io()" trait="_PNXRadarMarker1Mode" /></_Mode>
		<_XOffset><copy src="io()" trait="_PNXRadarMarker1X" /></_XOffset>
		<_YOffset><copy src="io()" trait="_PNXRadarMarker1Y" /></_YOffset>
	</image>
	
	<image name="Marker2">
		<include src="pnx\radar_marker.xml" />
		<_Mode><copy src="io()" trait="_PNXRadarMarker2Mode" /></_Mode>
		<_XOffset><copy src="io()" trait="_PNXRadarMarker2X" /></_XOffset>
		<_YOffset><copy src="io()" trait="_PNXRadarMarker2Y" /></_YOffset>
	</image>
	
	<image name="Marker3">
		<include src="pnx\radar_marker.xml" />
		<_Mode><copy src="io()" trait="_PNXRadarMarker3Mode" /></_Mode>
		<_XOffset><copy src="io()" trait="_PNXRadarMarker3X" /></_XOffset>
		<_YOffset><copy src="io()" trait="_PNXRadarMarker3Y" /></_YOffset>
	</image>
	
	<image name="Marker4">
		<include src="pnx\radar_marker.xml" />
		<_Mode><copy src="io()" trait="_PNXRadarMarker4Mode" /></_Mode>
		<_XOffset><copy src="io()" trait="_PNXRadarMarker4X" /></_XOffset>
		<_YOffset><copy src="io()" trait="_PNXRadarMarker4Y" /></_YOffset>
	</image>
	
	<image name="Marker5">
		<include src="pnx\radar_marker.xml" />
		<_Mode><copy src="io()" trait="_PNXRadarMarker5Mode" /></_Mode>
		<_XOffset><copy src="io()" trait="_PNXRadarMarker5X" /></_XOffset>
		<_YOffset><copy src="io()" trait="_PNXRadarMarker5Y" /></_YOffset>
	</image>
	
	<image name="Marker6">
		<include src="pnx\radar_marker.xml" />
		<_Mode><copy src="io()" trait="_PNXRadarMarker6Mode" /></_Mode>
		<_XOffset><copy src="io()" trait="_PNXRadarMarker6X" /></_XOffset>
		<_YOffset><copy src="io()" trait="_PNXRadarMarker6Y" /></_YOffset>
	</image>
	
	<image name="Marker7">
		<include src="pnx\radar_marker.xml" />
		<_Mode><copy src="io()" trait="_PNXRadarMarker7Mode" /></_Mode>
		<_XOffset><copy src="io()" trait="_PNXRadarMarker7X" /></_XOffset>
		<_YOffset><copy src="io()" trait="_PNXRadarMarker7Y" /></_YOffset>
	</image>
	
	<image name="Marker8">
		<include src="pnx\radar_marker.xml" />
		<_Mode><copy src="io()" trait="_PNXRadarMarker8Mode" /></_Mode>
		<_XOffset><copy src="io()" trait="_PNXRadarMarker8X" /></_XOffset>
		<_YOffset><copy src="io()" trait="_PNXRadarMarker8Y" /></_YOffset>
	</image>
	
	<image name="Marker9">
		<include src="pnx\radar_marker.xml" />
		<_Mode><copy src="io()" trait="_PNXRadarMarker9Mode" /></_Mode>
		<_XOffset><copy src="io()" trait="_PNXRadarMarker9X" /></_XOffset>
		<_YOffset><copy src="io()" trait="_PNXRadarMarker9Y" /></_YOffset>
	</image>
	
</rect>

<!-- ######################################################################################## Stealth Field Meter -->
<rect name="SFMeter">
	<locus> &true; </locus>
	<x>
		<copy src="screen()" trait="width" />
		<sub>
			<copy> 382 </copy>
			<mul src="globals()" trait="_duiscale_65" />
		</sub>
		<add src="globals()" trait="_HUDAPInfo_X" />
		<add src="globals()" trait="_SFMeter_X" />
	</x>
	<y>
		<copy src="ActionPoints" trait="y" />
		<sub>
			<copy> 52 </copy>
			<mul src="globals()" trait="_duiscale_65" />
		</sub>
		<add src="globals()" trait="_SFMeter_Y" />
	</y>
	<visible>
		<copy src="io()" trait="_PNXSFShowStealthMeter" />
		<eq> 1 </eq>
		<and src="io()" trait="_HUDMode" />
	</visible>
	<image name="SFMeterMeter">
		<depth> -1 </depth>
		<alpha> <copy src="io()" trait="_MeterAlpha" /> </alpha>
		<width>
			<copy> 152 </copy>
			<mul src="globals()" trait="_duiscale_65" />
			<mul src="me()" trait="_Value" />
		</width>
		<height>
			<copy> 20 </copy>
			<mul src="globals()" trait="_duiscale_65" />
		</height>
		<cropx>
			<copy src="parent()" trait="width"/>
			<mul src="me()" trait="_Value"/>
			<div> -1 </div>
		</cropx>
		
		<filename>
			<copy src="globals()" trait="_HUDSolidMeters" />
			<copy src="me()" trait="_filename_" />
		</filename>
		<_filename_0> Interface\HUD\hud_tick_mark.dds </_filename_0>
		<_filename_1> Interface\Shared\solid.dds </_filename_1>
		<zoom>
			<copy src="globals()" trait="_duiscale_65" />
			<mul> 100 </mul>
		</zoom>
		<tile> <not src="globals()" trait="_HUDSolidMeters" /> </tile>
		<x>
			<copy> 361 </copy>
			<mul src="globals()" trait="_duiscale_65" />
			<sub src="me()" trait="width"/>
		</x>
		<y>
			<copy> 61 </copy>
			<mul src="globals()" trait="_duiscale_65" />
			<sub src="me()" trait="height"/>
		</y>
		<_Value> <copy src="io()" trait="_PNXSFStability"/> </_Value>
		<systemcolor> <copy src="globals()" trait="_duiHUDMtrSysColor" /> </systemcolor> <!-- DarN CHECK -->
		<brightness> <copy src="globals()" trait="_duiHUDMtrBrightness" /> </brightness>
		<red> <copy src="globals()" trait="_HUDRed" /> </red>
		<green> <copy src="globals()" trait="_HUDGreen" /> </green>
		<blue> <copy src="globals()" trait="_HUDBlue" /> </blue>
	</image>
	<image name="SFMeterMeterBG">
		<visible> <copy src="globals()" trait="_HUDSolidMeters" /> </visible>
		<depth> -2 </depth>
		<filename> solid.dds </filename>
		<texatlas> Interface\InterfaceShared.tai </texatlas>
		<height> <copy src="sibling(SFMeterMeter)" trait="height" /> </height>
		<width>
			<copy> 152 </copy>
			<mul src="globals()" trait="_duiscale_65" />
		</width>
		<x>
			<copy src="sibling(SFMeterMeter)" trait="x" />
			<add src="sibling(SFMeterMeter)" trait="width" />
			<sub src="me()" trait="width" />
		</x>
		<y> <copy src="sibling(SFMeterMeter)" trait="y" /> </y>
		<alpha>
			<copy src="sibling(SFMeterMeter)" trait="alpha" />
			<div> 2 </div>
		</alpha>
		<brightness> <copy src="sibling(SFMeterMeter)" trait="brightness" /> </brightness>
		<systemcolor> <copy src="sibling(SFMeterMeter)" trait="systemcolor" /> </systemcolor> <!-- DarN CHECK -->
		<red> <copy src="globals()" trait="_HUDRed" /> </red>
		<green> <copy src="globals()" trait="_HUDGreen" /> </green>
		<blue> <copy src="globals()" trait="_HUDBlue" /> </blue>
	</image>
	<image name="SFBracket">
		<height>
			<copy> 152 </copy>
			<mul src="globals()" trait="_duiscale_65" />
		</height>
		<width>
			<copy> 512 </copy>
			<mul src="globals()" trait="_duiscale_65" />
		</width>
		<filename> Interface\HUD\glow_hud_right_sf_seperator.dds </filename>
		
		<filename>
			<copy src="io()" trait="_PNXSFMeterStyle" />
			<copy src="me()" trait="_filename_" />
		</filename>
		<_filename_0> Interface\HUD\glow_hud_right_sf_seperator.dds </_filename_0>
		<_filename_1> Interface\HUD\glow_hud_right_sf_seperator_nocond.dds </_filename_1>
		
		<zoom> &scale; </zoom>
		<brightness> <copy src="globals()" trait="_duiHUDBrightness" /> </brightness>
		<red> <copy src="globals()" trait="_HUDRed" /> </red>
		<green> <copy src="globals()" trait="_HUDGreen" /> </green>
		<blue> <copy src="globals()" trait="_HUDBlue" /> </blue>
	</image>
	<text name="SFLabel">
		<font> <copy src="globals()" trait="_HUDMeterFont" /> </font>
		<justify> &right; </justify>
		<x>
			<copy> 352 </copy>
			<mul src="globals()" trait="_duiscale_65" />
		</x>
		<y>
			<copy> 7 </copy>
			<mul src="globals()" trait="_duiscale_65" />
		</y>
		<string> SF </string>
		<brightness> <copy src="globals()" trait="_duiHUDBrightness" /> </brightness>
		<red> <copy src="globals()" trait="_HUDTxtRed" /> </red>
		<green> <copy src="globals()" trait="_HUDTxtGreen" /> </green>
		<blue> <copy src="globals()" trait="_HUDTxtBlue" /> </blue>
	</text>
	<text name="SFChargeText">
		<font> <copy src="globals()" trait="_HUDMeterFont" /> </font>
		<justify> &right; </justify>
		<x>
			<copy> 352 </copy>
			<mul src="globals()" trait="_duiscale_65" />
		</x>
		<y>
			<copy> 79 </copy>
			<mul src="globals()" trait="_duiscale_65" />
		</y>
		<string> <copy src="io()" trait="_PNXSFCharges"/> </string>
		<brightness> <copy src="globals()" trait="_duiHUDBrightness" /> </brightness>
		<red> <copy src="globals()" trait="_HUDTxtRed" /> </red>
		<green> <copy src="globals()" trait="_HUDTxtGreen" /> </green>
		<blue> <copy src="globals()" trait="_HUDTxtBlue" /> </blue>
	</text>
	<rect name="SFHealthMeterContainer">
		<include src="darn\hudmeter.xml" />
		<visible>
			<copy src="io()" trait="_PNXSFMeterStyle" />
			<eq> 0 </eq>
		</visible>
		<width> 40 </width>
		<height> 11 </height>
		<x>
			<copy> 176 </copy>
			<mul src="globals()" trait="_duiscale_65" />
		</x>
		<y>
			<copy> 84 </copy>
			<mul src="globals()" trait="_duiscale_65" />
		</y>
		<locus> &true; </locus>
		<_SolidMeter> &true; </_SolidMeter>
		<_ShowBackground> &true; </_ShowBackground>
		<alpha> <copy> 200 </copy> </alpha>
		<_Value> <copy src="io()" trait="_PNXSFHealth" /> </_Value>
	</rect>

</rect>

<!-- ######################################################################################## Crosshair -->
<rect name="PNXCrosshair">

	<visible>
		<copy src="io()" trait="_PNXCrosshairEnabled" />
		<eq> 1 </eq>
		<and src="ActionPoints" trait="visible" />
	</visible>

	<image name="PNXCrosshairLineW">
		<zoom> &scale; </zoom>
		<depth> 0 </depth>
		
		<width>
			<copy src="io()" trait="_PNXCrosshairLength" />
		</width>
		
		<height>
			<copy src="io()" trait="_PNXCrosshairWidth" />
		</height>
		
		<x>
			<copy src="screen()" trait="width" />
			<div> 2 </div>
			<sub>
				<copy src="me()" trait="width" />
			</sub>
			<sub src="io()" trait="_PNXCrosshairMinOffset" />
			<sub>
				<copy src="io()" trait="_PNXCrosshairMaxOffset" />
				<mul src="io()" trait="_PNXCrosshairSpread" />
			</sub>
		</x>
			
		<y>
			<copy src="screen()" trait="height" />
			<div> 2 </div>
			<sub>
				<copy src="me()" trait="height" />
				<div> 2 </div>
			</sub>
		</y>
		
		<filename> pnx\crosshairh.dds </filename>
	</image>
	
	<image name="PNXCrosshairLineE">
		<zoom> &scale; </zoom>
		<depth> 0 </depth>
		
		<width>
			<copy src="io()" trait="_PNXCrosshairLength" />
		</width>
		
		<height>
			<copy src="io()" trait="_PNXCrosshairWidth" />
		</height>
		
		<x>
			<copy src="screen()" trait="width" />
			<div> 2 </div>
			<add src="io()" trait="_PNXCrosshairMinOffset" />
			<add>
				<copy src="io()" trait="_PNXCrosshairMaxOffset" />
				<mul src="io()" trait="_PNXCrosshairSpread" />
			</add>
		</x>
			
		<y>
			<copy src="screen()" trait="height" />
			<div> 2 </div>
			<sub>
				<copy src="me()" trait="height" />
				<div> 2 </div>
			</sub>
		</y>
		
		<filename> pnx\crosshairh.dds </filename>
	</image>
	
	<image name="PNXCrosshairLineN">
		<zoom> &scale; </zoom>
		<depth> 0 </depth>
		
		<width>
			<copy src="io()" trait="_PNXCrosshairWidth" />
		</width>
		
		<height>
			<copy src="io()" trait="_PNXCrosshairLength" />
		</height>
		
		<x>
			<copy src="screen()" trait="width" />
			<div> 2 </div>
			<sub>
				<copy src="me()" trait="width" />
				<div> 2 </div>
			</sub>
		</x>
		
		<y>
			<copy src="screen()" trait="height" />
			<div> 2 </div>
			<sub>
				<copy src="me()" trait="height" />
			</sub>
			<sub src="io()" trait="_PNXCrosshairMinOffset" />
			<sub>
				<copy src="io()" trait="_PNXCrosshairMaxOffset" />
				<mul src="io()" trait="_PNXCrosshairSpread" />
			</sub>
		</y>
			
		<filename> pnx\crosshairv.dds </filename>
	</image>
	
	<image name="PNXCrosshairLineS">
		<zoom> &scale; </zoom>
		<depth> 0 </depth>
		
		<width>
			<copy src="io()" trait="_PNXCrosshairWidth" />
		</width>
		
		<height>
			<copy src="io()" trait="_PNXCrosshairLength" />
		</height>
		
		<x>
			<copy src="screen()" trait="width" />
			<div> 2 </div>
			<sub>
				<copy src="me()" trait="width" />
				<div> 2 </div>
			</sub>
		</x>
		
		<y>
			<copy src="screen()" trait="height" />
			<div> 2 </div>
			<add src="io()" trait="_PNXCrosshairMinOffset" />
			<add>
				<copy src="io()" trait="_PNXCrosshairMaxOffset" />
				<mul src="io()" trait="_PNXCrosshairSpread" />
			</add>
		</y>
			
		<filename> pnx\crosshairv.dds </filename>
	</image>
	
</rect>

<!-- ######################################################################################## Bullet Time Meter -->
<rect name="PNxBTMeter">
	<visible>
		<copy src="io()" trait="_PNxBTMeterEnabled" />
		<eq> 1 </eq>
	</visible>
	
	<x>
		<copy src="screen()" trait="width" />
		<!--mul> 0.74 </mul-->
		<mul> 0.5 </mul>
	</x>
	<y>
		<copy src="screen()" trait="height" />
		<!--mul> 0.94 </mul-->
		<mul> 0.1 </mul>
	</y>
	<width> 64 </width>
	<height> 64 </height>
	

	<image name="PNxBTMeterImage">
		<zoom> &scale; </zoom>
		<depth> 0 </depth>
		
		<x>
			<copy src="parent()" trait="x" />
			<sub>
				<copy src="me()" trait="width" />
				<div> 2 </div>
			</sub>
		</x>
		<y>
			<copy src="parent()" trait="y" />
			<sub>
				<copy src="me()" trait="height" />
				<div> 2 </div>
			</sub>
		</y>
		
		<width> <copy src="parent()" trait="width" /> </width>
		<height> <copy src="parent()" trait="height" /> </height>
		
		<alpha> 180 </alpha>

		<filename>
			<copy src="io()" trait="_PNxBTMeterAmount" />
			<copy src="me()" trait="_filename_" />
		</filename>
		<_filename_0> pnx\timemeter0.dds </_filename_0>
		<_filename_1> pnx\timemeter1.dds </_filename_1>
		<_filename_2> pnx\timemeter2.dds </_filename_2>
		<_filename_3> pnx\timemeter3.dds </_filename_3>
		<_filename_4> pnx\timemeter4.dds </_filename_4>
		<_filename_5> pnx\timemeter5.dds </_filename_5>
		<_filename_6> pnx\timemeter6.dds </_filename_6>
		<_filename_7> pnx\timemeter7.dds </_filename_7>
		<_filename_8> pnx\timemeter8.dds </_filename_8>
		<_filename_9> pnx\timemeter9.dds </_filename_9>
		<_filename_10> pnx\timemeter10.dds </_filename_10>
		<_filename_11> pnx\stopwatch.dds </_filename_11>
	</image>
	
	<image name="PNxBTMeterStatusWarning">
		<systemcolor> &nosystemcolor; </systemcolor>
	
		<visible>
			<copy src="io()" trait="_PNxBTMeterWarn" />
		</visible>
	
		<zoom> &scale; </zoom>
		<depth> 1 </depth>
		
		<x>
			<copy src="parent()" trait="x" />
			<sub>
				<copy src="me()" trait="width" />
				<div> 2 </div>
			</sub>
		</x>
		<y>
			<copy src="parent()" trait="y" />
			<sub>
				<copy src="me()" trait="height" />
				<div> 2 </div>
			</sub>
		</y>
		<width> <copy src="parent()" trait="width" /> </width>
		<height> <copy src="parent()" trait="height" /> </height>
		
		<alpha> 180 </alpha>

		<filename> pnx\timemeter_lowap.dds </filename>
	</image>
	
	<image name="PNxBTMeterStatusIcon">
	
		<visible>
			<not src="io()" trait="_PNxBTMeterWarn" />
			<and src="io()" trait="_PNxBTMeterIcon" />
			<gt> 0 </gt>
		</visible>
	
		<zoom> &scale; </zoom>
		<depth> 1 </depth>
		
		<x>
			<copy src="parent()" trait="x" />
			<sub>
				<copy src="me()" trait="width" />
				<div> 2 </div>
			</sub>
		</x>
		<y>
			<copy src="parent()" trait="y" />
			<sub>
				<copy src="me()" trait="height" />
				<div> 2 </div>
			</sub>
		</y>
		<width>
			<copy src="parent()" trait="width" />
			<!--mul>
				<copy> 0.9 </copy>
				<add>
					<copy> 0.1 </copy>
					<mul src="io()" trait="_PNxBTMeterIconAnim" />
				</add>
			</mul-->
		</width>
		<height>
			<copy src="me()" trait="width" />
		</height>
		
		<alpha>
			<copy> 180 </copy>
			<sub>
				<copy> 180 </copy>
				<mul src="io()" trait="_PNxBTMeterIconAnim" />
			</sub>
		
		</alpha>

		<filename>
			<copy src="io()" trait="_PNxBTMeterIcon" />
			<copy src="me()" trait="_filename_" />
		</filename>
		
		<_filename_1> pnx\timemeter_reaper.dds </_filename_1>
		
	</image>

</rect>


<!-- ######################################################################################## Crosshair -->
<rect name="PNXCalibrator">

	<visible>
		<copy src="io()" trait="_PNXCalibratorEnabled" />
		<eq> 1 </eq>
	</visible>
	
	<image name="PNXCalibratorImage">
		<zoom> &scale; </zoom>
		<depth> 1 </depth>
		
		<width>
			<copy src="io()" trait="_PNXCalibratorSize" />
			<div> 2 </div>
		</width>
		
		<height>
			<copy src="me()" trait="width" />
		</height>
		
		<x>
			<copy src="screen()" trait="width" />
			<div> 2 </div>
			<sub>
				<copy src="me()" trait="width" />
				<div> 2 </div>
			</sub>
		</x>
		
		<y>
			<copy src="screen()" trait="height" />
			<div> 2 </div>
			<sub>
				<copy src="me()" trait="height" />
				<div> 2 </div>
			</sub>
		</y>
			
		<filename> pnx\calibrator.dds </filename>
	</image>
	
	<text name="PNXCalibratorLabel">
		<justify> &center; </justify>
		<x>
			<copy src="screen()" trait="width" />
			<div> 2 </div>
		</x>
		
		<y>
			<copy src="screen()" trait="height" />
			<div> 2 </div>
			<add>
				<copy src="io()" trait="_PNXCalibratorSize" />
				<div> 2 </div>
			</add>
		</y>
		
		<string>
			<copy src="io()" trait="_PNXCalibratorSize" />
		</string>
	</text>
	
</rect>



<!-- ######################################################################################## Zoom Bar -->
<rect name="PNxZoomBar">

	<visible>
		<copy src="io()" trait="_PNxZoomBarEnabled" />
		<eq> 1 </eq>
	</visible>

	<x>
		<copy src="screen()" trait="width" />
		<sub src="me()" trait="width" />
		<sub> 20 </sub>
	</x>
	
	<y>
		<copy src="screen()" trait="height" />
		<div> 2 </div>
		<sub>
			<copy src="me()" trait="height" />
			<div> 2 </div>
		</sub>
	</y>
		
	<width> 64 </width>
	<height> 512 </height>

	<image name="PNxZoomBarFrame">
		<zoom> &scale; </zoom>
		<depth> 0 </depth>
		
		<alpha> 180 </alpha>
		
		<x>
			<copy src="parent()" trait="x" />
		</x>
	
		<y>
			<copy src="parent()" trait="y" />
		</y>
		
		<width>
			<copy src="parent()" trait="width" />
		</width>
	
		<height>
			<copy src="parent()" trait="height" />
		</height>
		
		<filename> pnx\zoombar.dds </filename>
	</image>
	
	<image name="PNxZoomBarMeter">
		<zoom> &scale; </zoom>
		<depth> -1 </depth>
		
		<alpha> 100 </alpha>
		
		<x>
			<copy src="parent()" trait="x" />
			<add> 30 </add>
		</x>
	
		<y>
			<copy src="parent()" trait="y" />
			<add> 15 </add>
			<add>
				<copy src="parent()" trait="height" />
				<sub> 30 </sub>
				<mul>
					<copy> 1 </copy>
					<sub src="io()" trait="_PNxZoomBarFill" />
				</mul>
			</add>
		</y>
		
		<width>
			<copy src="parent()" trait="width" />
			<sub> 45 </sub>
		</width>
	
		<height>
			<copy src="parent()" trait="height" />
			<sub> 30 </sub>
			<mul src="io()" trait="_PNxZoomBarFill" />
		</height>
		
		<filename> Interface\Shared\solid.dds </filename>
	</image>
	
	<image name="PNxZoomBarMeterArrowTop">
		<visible>
			<copy src="sibling(PNxZoomBarMeter)" trait="height" />
			<gt> 16 </gt>
		</visible>
		
		<zoom> &scale; </zoom>
		<depth> 0 </depth>
		
		<alpha> 100 </alpha>
		
		<x>
			<copy src="sibling(PNxZoomBarMeter)" trait="x" />
			<sub src="me()" trait="width" />
		</x>
	
		<y>
			<copy src="sibling(PNxZoomBarMeter)" trait="y" />
		</y>
		
		<width> 16 </width>
		<height> 16 </height>
		
		<filename> pnx\zoombar_arrow_top.dds </filename>
	</image>
	
	<image name="PNxZoomBarMeterArrowBottom">
		<visible>
			<copy src="sibling(PNxZoomBarMeterArrowTop)" trait="visible" />
		</visible>
	
		<zoom> &scale; </zoom>
		<depth> 0 </depth>
		
		<alpha> 100 </alpha>
		
		<x>
			<copy src="sibling(PNxZoomBarMeter)" trait="x" />
			<sub src="me()" trait="width" />
		</x>
	
		<y>
			<copy src="sibling(PNxZoomBarMeter)" trait="y" />
			<add src="sibling(PNxZoomBarMeter)" trait="height" />
			<sub src="me()" trait="height" />
		</y>
		
		<width> 16 </width>
		<height> 16 </height>
		
		<filename> pnx\zoombar_arrow_bottom.dds </filename>
	</image>
	
</rect>


<!-- ######################################################################################## Scanner -->
<rect name="PNxScanner">

	<visible>
		<copy src="io()" trait="_PNxScannerEnabled" />
		<eq> 1 </eq>
	</visible>

	<x>
		<copy> 20 </copy>
	</x>
	
	<y>
		<copy src="screen()" trait="height" />
		<div> 2 </div>
		<sub>
			<copy src="me()" trait="height" />
			<div> 2 </div>
		</sub>
	</y>
		
	<width> 64 </width>
	<height> 512 </height>

	<image name="PNxScannerFrame">
		<zoom> &scale; </zoom>
		<depth> 0 </depth>
		
		<alpha> 180 </alpha>
		
		<x>
			<copy src="parent()" trait="x" />
		</x>
	
		<y>
			<copy src="parent()" trait="y" />
		</y>
		
		<width>
			<copy src="parent()" trait="width" />
		</width>
	
		<height>
			<copy src="parent()" trait="height" />
		</height>
		
		<filename> pnx\scannerbracket.dds </filename>
	</image>
	
	<_text_pos_x>
		<copy src="me()" trait="x" />
		<add> 30 </add>
	</_text_pos_x> 
	
	<_text_pos_y>
		<copy src="me()" trait="y" />
		<add> 30 </add>
	</_text_pos_y>
	
	<_line_height> 31 </_line_height>
	<_indent_width> 20 </_indent_width>
	
	<image name="Cursor">
		<zoom> &scale; </zoom>
		<depth> 1 </depth>
		
		
		<visible>
			<copy src="io()" trait="_PNxScannerCursorBlink" />
			<eq> 0 </eq>
		</visible>
		
		<alpha> 200 </alpha>
		
		<x>
			<copy src="parent()" trait="_text_pos_x" />
			<add>
				<copy src="io()" trait="_PNxScannerCursorPos" />
				<mul> 15 </mul>
			</add>
			<add>
				<copy src="io()" trait="_PNxScannerCursorIndent" />
				<mul src="parent()" trait="_indent_width" />
			</add>
			
		</x>

		<y>
			<copy src="parent()" trait="_text_pos_y" />
			<add>
				<copy src="io()" trait="_PNxScannerCursorLine" />
				<mul src="parent()" trait="_line_height" />
			</add>
			<sub> 4 </sub>
		</y>
		
		<width> 11 </width>
		<height> 22 </height>
		
		<filename> Interface\Shared\solid.dds </filename>
	</image>
	
	<text name="PNxScannerText1">
		<include src="pnx\floating_text.xml" />
	
		<_line> 0 </_line>
	
		<_dat_1>W</_dat_1>
		<_dat_2>WA</_dat_2>
		<_dat_3>WAI</_dat_3>
		<_dat_4>WAIT</_dat_4>
		<_dat_5>WAITI</_dat_5>
		<_dat_6>WAITIN</_dat_6>
		<_dat_7>WAITING</_dat_7>
		<_dat_8>WAITING.</_dat_8>
		<_dat_9>WAITING..</_dat_9>
		<_dat_10>WAITING...</_dat_10>
		
		<_dat_11>S</_dat_11>
		<_dat_12>SC</_dat_12>
		<_dat_13>SCA</_dat_13>
		<_dat_14>SCAN</_dat_14>
		<_dat_15>SCANN</_dat_15>
		<_dat_16>SCANNI</_dat_16>
		<_dat_17>SCANNIN</_dat_17>
		<_dat_18>SCANNING</_dat_18>
		<_dat_19>SCANNING.</_dat_19>
		<_dat_20>SCANNING..</_dat_20>
		<_dat_21>SCANNING...</_dat_21>
		
		<_index><copy src="io()" trait="_PNxScannerText1Index" /></_index>
	</text>
	
	<text name="PNxScannerText2">
		<include src="pnx\floating_text.xml" />
	
		<_line> 2 </_line>
	
		<_dat_1>A</_dat_1>
		<_dat_2>AL</_dat_2>
		<_dat_3>ALE</_dat_3>
		<_dat_4>ALER</_dat_4>
		<_dat_5>ALERT</_dat_5>
		<_dat_6>ALERTN</_dat_6>
		<_dat_7>ALERTNE</_dat_7>
		<_dat_8>ALERTNES</_dat_8>
		<_dat_9>ALERTNESS</_dat_9>
		<_dat_10>ALERTNESS:</_dat_10>
		
		<_index><copy src="io()" trait="_PNxScannerText2Index" /></_index>
	</text>
	
	<text name="PNxScannerText3">
	
		<include src="pnx\floating_text.xml" />
	
		<_line> 3 </_line>
		<_indent> 2 </_indent>
	
		<_dat_1>h</_dat_1>
		<_dat_2>hi</_dat_2>
		<_dat_3>hig</_dat_3>
		<_dat_4>high</_dat_4>
		
		<_dat_5>m</_dat_5>
		<_dat_6>me</_dat_6>
		<_dat_7>med</_dat_7>
		<_dat_8>medi</_dat_8>
		<_dat_9>mediu</_dat_9>
		<_dat_10>medium</_dat_10>
		
		<_dat_11>l</_dat_11>
		<_dat_12>lo</_dat_12>
		<_dat_13>low</_dat_13>
		
		<_index><copy src="io()" trait="_PNxScannerText3Index" /></_index>
		
	</text>
	
	<text name="PNxScannerText4">
		<include src="pnx\floating_text.xml" />
	
		<_line> 5 </_line>
	
		<_dat_1>A</_dat_1>
		<_dat_2>AR</_dat_2>
		<_dat_3>ARM</_dat_3>
		<_dat_4>ARMO</_dat_4>
		<_dat_5>ARMOR</_dat_5>
		<_dat_6>ARMOR R</_dat_6>
		<_dat_7>ARMOR RA</_dat_7>
		<_dat_8>ARMOR RAT</_dat_8>
		<_dat_9>ARMOR RATI</_dat_9>
		<_dat_10>ARMOR RATIN</_dat_10>
		<_dat_11>ARMOR RATING</_dat_11>
		<_dat_12>ARMOR RATING:</_dat_12>
		
		<_index><copy src="io()" trait="_PNxScannerText4Index" /></_index>
	</text>
	
	<text name="PNxScannerText5">
		<include src="pnx\floating_text.xml" />
	
		<_line> 6 </_line>
		<_indent> 2 </_indent>
	
		<_dat_1>h</_dat_1>
		<_dat_2>hi</_dat_2>
		<_dat_3>hig</_dat_3>
		<_dat_4>high</_dat_4>
		
		<_dat_5>m</_dat_5>
		<_dat_6>me</_dat_6>
		<_dat_7>med</_dat_7>
		<_dat_8>medi</_dat_8>
		<_dat_9>mediu</_dat_9>
		<_dat_10>medium</_dat_10>
		
		<_dat_11>l</_dat_11>
		<_dat_12>lo</_dat_12>
		<_dat_13>low</_dat_13>
		
		<_index><copy src="io()" trait="_PNxScannerText5Index" /></_index>
	</text>
	
	<text name="PNxScannerText6">
		<include src="pnx\floating_text.xml" />
	
		<_line> 8 </_line>
	
		<_dat_1>T</_dat_1>
		<_dat_2>TH</_dat_2>
		<_dat_3>THR</_dat_3>
		<_dat_4>THRE</_dat_4>
		<_dat_5>THREA</_dat_5>
		<_dat_6>THREAT</_dat_6>
		<_dat_7>THREAT R</_dat_7>
		<_dat_8>THREAT RA</_dat_8>
		<_dat_9>THREAT RAT</_dat_9>
		<_dat_10>THREAT RATI</_dat_10>
		<_dat_11>THREAT RATIN</_dat_11>
		<_dat_12>THREAT RATING</_dat_12>
		<_dat_13>THREAT RATING:</_dat_13>
		
		<_index><copy src="io()" trait="_PNxScannerText6Index" /></_index>
	</text>
	
	<text name="PNxScannerText7">
		<include src="pnx\floating_text.xml" />
	
		<_line> 9 </_line>
		<_indent> 2 </_indent>
	
		<_dat_1>h</_dat_1>
		<_dat_2>hi</_dat_2>
		<_dat_3>hig</_dat_3>
		<_dat_4>high</_dat_4>
		
		<_dat_5>m</_dat_5>
		<_dat_6>me</_dat_6>
		<_dat_7>med</_dat_7>
		<_dat_8>medi</_dat_8>
		<_dat_9>mediu</_dat_9>
		<_dat_10>medium</_dat_10>
		
		<_dat_11>l</_dat_11>
		<_dat_12>lo</_dat_12>
		<_dat_13>low</_dat_13>
		
		<_index><copy src="io()" trait="_PNxScannerText7Index" /></_index>
	</text>
	
	<text name="PNxScannerText8">
		<include src="pnx\floating_text.xml" />
	
		<_line> 11 </_line>
	
		<_dat_1>W</_dat_1>
		<_dat_2>WE</_dat_2>
		<_dat_3>WEA</_dat_3>
		<_dat_4>WEAK</_dat_4>
		<_dat_5>WEAKN</_dat_5>
		<_dat_6>WEAKNE</_dat_6>
		<_dat_7>WEAKNES</_dat_7>
		<_dat_8>WEAKNESS</_dat_8>
		<_dat_9>WEAKNESS:</_dat_9>
		
		<_index><copy src="io()" trait="_PNxScannerText8Index" /></_index>
	</text>
	
	<text name="PNxScannerText9">
		<include src="pnx\floating_text.xml" />
	
		<_line> 12 </_line>
		<_indent> 2 </_indent>
	
		<_dat_1>h</_dat_1>
		<_dat_2>he</_dat_2>
		<_dat_3>hea</_dat_3>
		<_dat_4>head</_dat_4>
		
		<_dat_5>l</_dat_5>
		<_dat_6>le</_dat_6>
		<_dat_7>lef</_dat_7>
		<_dat_8>left</_dat_8>
		<_dat_9>left a</_dat_9>
		<_dat_10>left ar</_dat_10>
		<_dat_11>left arm</_dat_11>
		
		<_dat_12>r</_dat_12>
		<_dat_13>ri</_dat_13>
		<_dat_14>rig</_dat_14>
		<_dat_15>righ</_dat_15>
		<_dat_16>right</_dat_16>
		<_dat_17>right a</_dat_17>
		<_dat_18>right ar</_dat_18>
		<_dat_19>right arm</_dat_19>
		
		<_dat_20>t</_dat_20>
		<_dat_21>to</_dat_21>
		<_dat_22>tor</_dat_22>
		<_dat_23>tors</_dat_23>
		<_dat_24>torso</_dat_24>
		
		<_dat_25>l</_dat_25>
		<_dat_26>le</_dat_26>
		<_dat_27>lef</_dat_27>
		<_dat_28>left</_dat_28>
		<_dat_29>left l</_dat_29>
		<_dat_30>left le</_dat_30>
		<_dat_31>left leg</_dat_31>
		
		<_dat_32>r</_dat_32>
		<_dat_33>ri</_dat_33>
		<_dat_34>rig</_dat_34>
		<_dat_35>righ</_dat_35>
		<_dat_36>right</_dat_36>
		<_dat_37>right l</_dat_37>
		<_dat_38>right le</_dat_38>
		<_dat_39>right leg</_dat_39>
		
		<_index><copy src="io()" trait="_PNxScannerText9Index" /></_index>
	</text>
	
	<text name="PNxScannerText10">
		<include src="pnx\floating_text.xml" />
	
		<_line> 14 </_line>
	
		<_dat_1>D</_dat_1>
		<_dat_2>DO</_dat_2>
		<_dat_3>DON</_dat_3>
		<_dat_4>DONE</_dat_4>
		<_dat_5>DONE.</_dat_5>
		
		<_index><copy src="io()" trait="_PNxScannerText10Index" /></_index>
	</text>
	
</rect>